setup.py
msgpack_tool/__init__.py
msgpack_tool.egg-info/PKG-INFO
msgpack_tool.egg-info/SOURCES.txt
msgpack_tool.egg-info/dependency_links.txt
msgpack_tool.egg-info/entry_points.txt
msgpack_tool.egg-info/requires.txt
msgpack_tool.egg-info/top_level.txt