Metadata-Version: 1.0
Name: msgpack-tool
Version: 0.0.1
Summary: a cli utility for msgpack/json conversion
Home-page: https://github.com/zweifisch/msgpack-tool
Author: Feng Zhou
Author-email: zf.pascal@gmail.com
License: UNKNOWN
Platform: UNKNOWN
